{
  "logo_candidates": [
    "C:/Users/engenharia/VSCodeProjects/teste/dist/Logos/image.jpg",
    "C:/Users/engenharia/VSCodeProjects/teste/Logos/logo(1).jpg",
    "C:\\Users\\engenharia\\VSCodeProjects\\teste\\Logos/image (1).jpg",
    "C:\\Users\\engenharia\\VSCodeProjects\\teste\\Logos/image.jpg",
    "C:\\Users\\engenharia\\VSCodeProjects\\teste\\Logos/logo.png",
    "C:\\Users\\engenharia\\VSCodeProjects\\teste\\logo.jpg",
    "C:\\Users\\engenharia\\VSCodeProjects\\teste\\Logos/logo(1).jpg",
    "logo.png",
    "C:\\Users\\engenharia\\VSCodeProjects\\teste\\logo.png",
    "C:\\Users\\engenharia\\VSCodeProjects\\teste\\Logos\\logo.png",
    "C:\\Users\\engenharia\\VSCodeProjects\\teste\\Logos\\image (1).jpg",
    "C:\\Users\\engenharia\\VSCodeProjects\\teste\\Logos\\image.jpg",
    "C:\\Users\\engenharia\\VSCodeProjects\\teste\\Logos\\logo(1).jpg"
  ],
  "empresa_info_rodape": [
    "Barcelbal - Balanças e Básculas, S.A.",
    "Rua dos Canteiros, nº 53 - Adaufe",
    "Tel: 253 606 590  |  Email: geral@barcelbal.pt",
    "NIF: 502403843  |  Capital Social: 100.000 €"
  ],
  "guia_emitente": {
    "nome": "Barcelbal - Balanças e Básculas, S.A.",
    "nif": "502403843",
    "morada": "Rua dos Canteiros, nº 53 - Adaufe",
    "local_carga": "Rua dos Canteiros, nº 53 - Adaufe"
  },
  "guia_info_extra": [],
  "primary_color": "#000040"
}